{
  "type": "generic",
  "id": "front-grille-speedster-vx220-turbo-A26D1C",
  "title": "Front Grille - Speedster/VX220 Turbo",
  "htmlContent": "<div class=\"content\">\n\r\n<table width=\"100%\" >\r\n  <!--XPRINT-->\r\n  <table>\r\n  <tr>\r\n    <td></td>\r\n   <td>&nbsp;&nbsp;&nbsp;&nbsp;&nbsp;&nbsp;&nbsp;&nbsp;&nbsp;&nbsp;&nbsp;&nbsp;&nbsp;</td>\r\n  \t\r\n  </tr>\r\n  </table>\r\n  \r\n  <!--/XPRINT-->\r\n  <tr>\r\n    <td >\n<p class=\"title\">Front Grille - Speedster/VX220 Turbo</p>\n\n<table border=\"0\">\n<tr>\n<td></td>\n</tr>\n\n<tr>\n<td><!--SCDS Link: S0004922.itf-->\n<img border=\"0\" width=\"650\" height=\"425\" alt=\n\"Object Number: 2421903  Size: DEFAULT\" align=\"TOP\" src=\"/data/assets/images/6ed6e2a06c1d.jpg\">\n<br>\n<a href=\"javascript:TFormSubmit('AEXH1CMH1XKH1','1','AEXH1CMH1XKH1','detail')\">\n<img src=\"/data/assets/images/db1138827f57.gif\" alt=\n\"Click here for detailed picture of above image\"></a>\n\n<br> </td>\n</tr>\n\n<tr>\n<td>\n<p>For Opel vehicles, the front grille is re-styled. The familiar\nhorizontal bar has been removed and the Opel badge is centrally\nmounted on a plinth, which incorporates the fixing point for the\nremovable towing eye.</p>\n</td>\n</tr>\n</table>\n\n<br>\n</td>\r\n  </tr>\r\n  \r\n  <tr>\r\n    <td ></td>\r\n  </tr>\r\n</table>\r\n</div>",
  "extractedData": {}
}