{
  "diagramId": "028ba4338f19",
  "imageWidth": 1240,
  "imageHeight": 1761,
  "sheetCode": {
    "text": "J1",
    "bbox": {
      "x": 160,
      "y": 1610,
      "width": 39,
      "height": 32
    }
  },
  "hotspots": [
    {
      "type": "polygon",
      "ref": 8,
      "points": [
        {
          "x": 334,
          "y": 979
        },
        {
          "x": 323,
          "y": 996
        },
        {
          "x": 303,
          "y": 1011
        },
        {
          "x": 241,
          "y": 1023
        },
        {
          "x": 228,
          "y": 1015
        },
        {
          "x": 227,
          "y": 995
        },
        {
          "x": 231,
          "y": 989
        },
        {
          "x": 334,
          "y": 930
        },
        {
          "x": 347,
          "y": 924
        },
        {
          "x": 355,
          "y": 926
        },
        {
          "x": 363,
          "y": 939
        },
        {
          "x": 337,
          "y": 975
        }
      ],
      "confidence": 100,
      "manual": true
    },
    {
      "type": "polygon",
      "ref": 7,
      "points": [
        {
          "x": 417,
          "y": 1188
        },
        {
          "x": 232,
          "y": 1298
        },
        {
          "x": 213,
          "y": 1305
        },
        {
          "x": 203,
          "y": 1291
        },
        {
          "x": 204,
          "y": 1189
        },
        {
          "x": 404,
          "y": 1073
        },
        {
          "x": 429,
          "y": 1084
        },
        {
          "x": 411,
          "y": 1113
        },
        {
          "x": 414,
          "y": 1179
        }
      ],
      "confidence": 100,
      "manual": true
    },
    {
      "type": "rect",
      "ref": 9,
      "bbox": {
        "x": 478.14415675297414,
        "y": 1039.593839967059,
        "width": 134.32400279916027,
        "height": 50.5255423372987
      },
      "normalized": {
        "x": 0.38560012641368885,
        "y": 0.5994401668818202,
        "width": 0.10733199395020206,
        "height": 0.019594121763470893
      },
      "confidence": 100,
      "manual": true
    },
    {
      "type": "polygon",
      "ref": 6,
      "points": [
        {
          "x": 550,
          "y": 924
        },
        {
          "x": 550,
          "y": 942
        },
        {
          "x": 545,
          "y": 946
        },
        {
          "x": 535,
          "y": 943
        },
        {
          "x": 527,
          "y": 930
        },
        {
          "x": 523,
          "y": 907
        },
        {
          "x": 542,
          "y": 902
        },
        {
          "x": 550,
          "y": 923
        }
      ],
      "confidence": 100,
      "manual": true
    },
    {
      "type": "polygon",
      "ref": 1,
      "points": [
        {
          "x": 733,
          "y": 891
        },
        {
          "x": 739,
          "y": 915
        },
        {
          "x": 799,
          "y": 991
        },
        {
          "x": 810,
          "y": 1027
        },
        {
          "x": 805,
          "y": 1045
        },
        {
          "x": 769,
          "y": 1065
        },
        {
          "x": 758,
          "y": 1057
        },
        {
          "x": 689,
          "y": 881
        },
        {
          "x": 650,
          "y": 860
        },
        {
          "x": 644,
          "y": 850
        },
        {
          "x": 642,
          "y": 819
        },
        {
          "x": 635,
          "y": 797
        },
        {
          "x": 638,
          "y": 789
        },
        {
          "x": 669,
          "y": 772
        },
        {
          "x": 685,
          "y": 756
        },
        {
          "x": 702,
          "y": 757
        },
        {
          "x": 723,
          "y": 783
        },
        {
          "x": 723,
          "y": 835
        },
        {
          "x": 733,
          "y": 888
        }
      ],
      "confidence": 100,
      "manual": true
    },
    {
      "type": "polygon",
      "ref": 2,
      "points": [
        {
          "x": 906,
          "y": 1042
        },
        {
          "x": 905,
          "y": 1066
        },
        {
          "x": 859,
          "y": 1090
        },
        {
          "x": 852,
          "y": 1084
        },
        {
          "x": 827,
          "y": 1022
        },
        {
          "x": 830,
          "y": 1016
        },
        {
          "x": 867,
          "y": 994
        },
        {
          "x": 882,
          "y": 991
        },
        {
          "x": 895,
          "y": 1010
        },
        {
          "x": 905,
          "y": 1038
        }
      ],
      "confidence": 100,
      "manual": true
    },
    {
      "type": "polygon",
      "ref": 4,
      "points": [
        {
          "x": 936,
          "y": 994
        },
        {
          "x": 928,
          "y": 1003
        },
        {
          "x": 915,
          "y": 1003
        },
        {
          "x": 907,
          "y": 1009
        },
        {
          "x": 897,
          "y": 998
        },
        {
          "x": 898,
          "y": 991
        },
        {
          "x": 914,
          "y": 980
        },
        {
          "x": 932,
          "y": 984
        },
        {
          "x": 937,
          "y": 992
        }
      ],
      "confidence": 100,
      "manual": true
    },
    {
      "type": "polygon",
      "ref": 5,
      "points": [
        {
          "x": 935,
          "y": 718
        },
        {
          "x": 920,
          "y": 728
        },
        {
          "x": 910,
          "y": 725
        },
        {
          "x": 877,
          "y": 745
        },
        {
          "x": 870,
          "y": 743
        },
        {
          "x": 862,
          "y": 730
        },
        {
          "x": 866,
          "y": 722
        },
        {
          "x": 898,
          "y": 704
        },
        {
          "x": 900,
          "y": 695
        },
        {
          "x": 915,
          "y": 686
        },
        {
          "x": 932,
          "y": 698
        },
        {
          "x": 936,
          "y": 714
        }
      ],
      "confidence": 100,
      "manual": true
    },
    {
      "type": "polygon",
      "ref": 3,
      "points": [
        {
          "x": 962,
          "y": 1052
        },
        {
          "x": 953,
          "y": 1063
        },
        {
          "x": 922,
          "y": 1063
        },
        {
          "x": 915,
          "y": 1056
        },
        {
          "x": 917,
          "y": 1044
        },
        {
          "x": 947,
          "y": 1034
        },
        {
          "x": 956,
          "y": 1036
        },
        {
          "x": 962,
          "y": 1049
        }
      ],
      "confidence": 100,
      "manual": true
    }
  ],
  "extractedAt": "2026-02-02T13:54:47.734Z",
  "status": "done",
  "modifiedAt": "2026-02-14T22:16:05.055Z"
}