{
  "diagramId": "b1244dc56d93",
  "imageWidth": 1240,
  "imageHeight": 1761,
  "sheetCode": {
    "text": "B5",
    "bbox": {
      "x": 160,
      "y": 1609,
      "width": 49,
      "height": 33
    },
    "confidence": 92
  },
  "hotspots": [
    {
      "ref": 2,
      "bbox": {
        "x": 666,
        "y": 992,
        "width": 11,
        "height": 18
      },
      "normalized": {
        "x": 0.5370967741935484,
        "y": 0.5633162975582056,
        "width": 0.008870967741935484,
        "height": 0.010221465076660987
      },
      "confidence": 97
    },
    {
      "ref": 3,
      "bbox": {
        "x": 524,
        "y": 175,
        "width": 13,
        "height": 20
      },
      "normalized": {
        "x": 0.42258064516129035,
        "y": 0.09937535491198182,
        "width": 0.010483870967741936,
        "height": 0.011357183418512209
      },
      "confidence": 96
    },
    {
      "ref": 5,
      "bbox": {
        "x": 750,
        "y": 171,
        "width": 12,
        "height": 19
      },
      "normalized": {
        "x": 0.6048387096774194,
        "y": 0.09710391822827939,
        "width": 0.00967741935483871,
        "height": 0.010789324247586598
      },
      "confidence": 97
    }
  ],
  "extractedAt": "2026-02-02T13:56:45.784Z"
}