{
  "diagramId": "c6ebb1265e09",
  "imageWidth": 1240,
  "imageHeight": 1761,
  "sheetCode": {
    "text": "P2",
    "bbox": {
      "x": 156,
      "y": 1614,
      "width": 45,
      "height": 31
    },
    "confidence": 24
  },
  "hotspots": [
    {
      "ref": 2,
      "bbox": {
        "x": 407,
        "y": 1409,
        "width": 19,
        "height": 22
      },
      "normalized": {
        "x": 0.3282258064516129,
        "y": 0.8001135718341851,
        "width": 0.01532258064516129,
        "height": 0.01249290176036343
      },
      "confidence": 60
    },
    {
      "ref": 2,
      "bbox": {
        "x": 894,
        "y": 1534,
        "width": 12,
        "height": 18
      },
      "normalized": {
        "x": 0.7209677419354839,
        "y": 0.8710959681998864,
        "width": 0.00967741935483871,
        "height": 0.010221465076660987
      },
      "confidence": 97
    },
    {
      "ref": 5,
      "bbox": {
        "x": 640,
        "y": 1179,
        "width": 177,
        "height": 130
      },
      "normalized": {
        "x": 0.5161290322580645,
        "y": 0.6695059625212947,
        "width": 0.14274193548387096,
        "height": 0.07382169222032936
      },
      "confidence": 9
    },
    {
      "ref": 7,
      "bbox": {
        "x": 508,
        "y": 570,
        "width": 154,
        "height": 59
      },
      "normalized": {
        "x": 0.4096774193548387,
        "y": 0.32367972742759793,
        "width": 0.12419354838709677,
        "height": 0.033503691084611015
      },
      "confidence": 17
    },
    {
      "ref": 10,
      "bbox": {
        "x": 226,
        "y": 1414,
        "width": 23,
        "height": 19
      },
      "normalized": {
        "x": 0.18225806451612903,
        "y": 0.8029528676888131,
        "width": 0.018548387096774192,
        "height": 0.010789324247586598
      },
      "confidence": 96
    }
  ],
  "extractedAt": "2026-02-02T13:57:06.342Z"
}