{
  "type": "generic",
  "id": "engine-cover-A26D1C",
  "title": "engine-cover-A26D1C",
  "htmlContent": "<div class=\"content\">\n\r\n<table width=\"100%\" >\r\n  <!--XPRINT-->\r\n  <table>\r\n  <tr>\r\n    <td><a href=\"#relatedlus\">Related Literature Units</a></td>\r\n   <td>&nbsp;&nbsp;&nbsp;&nbsp;&nbsp;&nbsp;&nbsp;&nbsp;&nbsp;&nbsp;&nbsp;&nbsp;&nbsp;</td>\r\n  \t\r\n  </tr>\r\n  </table>\r\n  <tr><td><hr size=\"1\" ></td></tr>\r\n  <!--/XPRINT-->\r\n  <tr>\r\n    <td >\r\n<DIV>\r\n<P  ><FONT STYLE=\"font-size: 12pt; \">         &nbsp;</FONT><P  ><FONT STYLE=\"font-size: 12pt;font-weight: bold; \"> Engine Cover   &nbsp;</FONT><P  ><FONT STYLE=\"font-size: 12pt; \"> The engine cover is attached to the body by means of a hinge at the front edge.   The engine cover lock is operated by means of a cable.   &nbsp;</FONT><P  ><FONT STYLE=\"font-size: 12pt; \"> The engine cover is equipped with two grilles for the passage of air from the  engine compartment (see Section 2.5.2  \"Rear Grilles, Engine Compartment\").   &nbsp;</FONT></DIV>\r\n<DIV>\r\n<P  ><FONT STYLE=\"font-size: 12pt; \">  &nbsp;</FONT><P ALIGN=\"right\" ><!-- SCDS: T9164.TIF -->\r\n<IMG src=\"/data/assets/images/f6a25bd622f1.jpg\" ALIGN=\"TOP\" ALT=\"Object Number: 2429554  Size: DEFAULT\" HEIGHT=634 WIDTH=747 BORDER=0 USEMAP=\"#2429554.map\"><br><a href=\"javascript:TFormSubmit('AZYH1SJH1OHH1','1','AZYH1SJH1OHH1','detail')\"><img src=\"/data/assets/images/db1138827f57.gif\" alt=\"Click here for detailed picture of above image\"></a>&nbsp;<P  ><FONT STYLE=\"font-size: 12pt; \">  &nbsp;</FONT></DIV>\r\n<DIV>\r\n<P  ><FONT STYLE=\"font-size: 12pt; \">    &nbsp;</FONT></DIV>\r\n<DIV>\r\n<P  >&nbsp;&nbsp;</DIV>\r\n<DIV>\r\n<P  ><FONT STYLE=\"font-size: 12pt; \">       &nbsp;</FONT></DIV>\r\n</td>\r\n  </tr>\r\n  <tr><td><hr size=\"1\" ></td></tr>\r\n  <tr>\r\n    <td ><a id=\"relatedlus\"></a><table ><tr ><th colspan=\"2\" >Related Literature Units</th></tr><tr ><td >-</td><td ><a href=\"javascript:TFormSubmit('AV5I17JH1FNH1','1','AV5I17JH1FNH1','_top')\" id=\"AV5I17JH1FNH1\" >Rear Grilles, Engine Compartment</a></td></tr></table></td>\r\n  </tr>\r\n</table>\r\n</div>",
  "extractedData": {}
}